{
	"log": [
		{
			"DateTime": "Date: 2022-4-30 Time:  10 : 2 : 35",
			"UserId": "latest",
			"Errormsg": "TypeError: Cannot read properties of undefined (reading 'id')"
		},
		{
			"DateTime": "Date: 2022-4-30 Time:  10 : 3 : 54",
			"UserId": "latest",
			"Errormsg": "TypeError: Cannot read properties of undefined (reading 'id')"
		},
		{
			"DateTime": "Date: 2022-4-30 Time:  10 : 5 : 26",
			"UserId": "latest",
			"Errormsg": "TypeError: Cannot read properties of undefined (reading 'id')"
		},
		{
			"DateTime": "Date: 2022-4-30 Time:  22 : 38 : 39",
			"UserId": "latest",
			"Errormsg": "TypeError: Cannot read properties of undefined (reading 'status')"
		},
		{
			"DateTime": "Date: 2022-4-30 Time:  23 : 20 : 44",
			"UserId": "latest",
			"Errormsg": "TypeError: Cannot read properties of undefined (reading 'status')"
		},
		{
			"DateTime": "Date: 2022-4-30 Time:  23 : 42 : 39",
			"UserId": "latest",
			"Errormsg": "TypeError: Cannot read properties of undefined (reading 'status')"
		},
		{
			"DateTime": "Date: 2022-4-30 Time:  23 : 44 : 3",
			"UserId": "latest",
			"Errormsg": "TypeError: Cannot read properties of undefined (reading 'status')"
		},
		{
			"DateTime": "Date: 2022-4-31 Time:  0 : 20 : 49",
			"UserId": "latest",
			"Errormsg": "TypeError: Cannot read properties of undefined (reading 'status')"
		},
		{
			"DateTime": "Date: 2022-4-31 Time:  3 : 26 : 10",
			"UserId": "latest",
			"Errormsg": "ReferenceError: res is not defined"
		},
		{
			"DateTime": "Date: 2022-5-1 Time:  21 : 58 : 54",
			"UserId": "latest",
			"Errormsg": "ReferenceError: res is not defined"
		},
		{
			"DateTime": "Date: 2022-5-1 Time:  22 : 22 : 35",
			"UserId": "latest",
			"Errormsg": "ReferenceError: res is not defined"
		},
		{
			"DateTime": "Date: 2022-5-2 Time:  23 : 13 : 44",
			"UserId": "latest",
			"Errormsg": "TypeError: Cannot read properties of undefined (reading 'validatedata')"
		},
		{
			"DateTime": "Date: 2022-5-2 Time:  23 : 15 : 13",
			"UserId": "latest",
			"Errormsg": "TypeError: Cannot read properties of undefined (reading 'validatedata')"
		},
		{
			"DateTime": "Date: 2022-5-2 Time:  23 : 15 : 25",
			"UserId": "latest",
			"Errormsg": "TypeError: Cannot read properties of undefined (reading 'validatedata')"
		},
		{
			"DateTime": "Date: 2022-5-2 Time:  23 : 17 : 37",
			"UserId": "latest",
			"Errormsg": "TypeError: Cannot read properties of undefined (reading 'validatedata')"
		},
		{
			"DateTime": "Date: 2022-5-2 Time:  23 : 18 : 38",
			"UserId": "latest",
			"Errormsg": "TypeError: Cannot read properties of undefined (reading 'validatedata')"
		},
		{
			"DateTime": "Date: 2022-5-2 Time:  23 : 19 : 29",
			"UserId": "latest",
			"Errormsg": "TypeError: Cannot read properties of undefined (reading 'validatedata')"
		},
		{
			"DateTime": "Date: 2022-5-2 Time:  23 : 21 : 49",
			"UserId": "latest",
			"Errormsg": "TypeError: Urls.Books.books_validationschema is not a function"
		},
		{
			"DateTime": "Date: 2022-5-2 Time:  23 : 22 : 1",
			"UserId": "latest",
			"Errormsg": "TypeError: Urls.Books.books_validationschema is not a function"
		},
		{
			"DateTime": "Date: 2022-5-2 Time:  23 : 24 : 25",
			"UserId": "latest",
			"Errormsg": "TypeError: Cannot read properties of undefined (reading 'validatedata')"
		},
		{
			"DateTime": "Date: 2022-5-2 Time:  23 : 26 : 50",
			"UserId": "latest",
			"Errormsg": "TypeError: Cannot read properties of undefined (reading 'validatedata')"
		},
		{
			"DateTime": "Date: 2022-5-2 Time:  23 : 28 : 12",
			"UserId": "latest",
			"Errormsg": "TypeError: Cannot read properties of undefined (reading 'validatedata')"
		}
	]
}
